datetime_distance/__init__.py
datetime_distance-0.1.2.dist-info/top_level.txt
datetime_distance-0.1.2.dist-info/METADATA
datetime_distance-0.1.2.dist-info/DESCRIPTION.rst
datetime_distance-0.1.2.dist-info/metadata.json
datetime_distance-0.1.2.dist-info/WHEEL
datetime_distance-0.1.2.dist-info/RECORD
