Metadata-Version: 2.0
Name: datetime-distance
Version: 0.1.2
Summary: Compare string distances between dates, timestamps, or datetime objects.
Home-page: https://github.com/dedupeio/datetime-distance
Author: UNKNOWN
Author-email: UNKNOWN
License: The MIT License: http://www.opensource.org/licenses/mit-license.php
Platform: UNKNOWN
Classifier: Intended Audience :: Developers
Classifier: Intended Audience :: Science/Research
Classifier: License :: OSI Approved :: MIT License
Classifier: Natural Language :: English
Classifier: Operating System :: MacOS :: MacOS X
Classifier: Operating System :: Microsoft :: Windows
Classifier: Operating System :: POSIX
Classifier: Programming Language :: Python
Classifier: Topic :: Software Development :: Libraries :: Python Modules
Classifier: Topic :: Scientific/Engineering
Classifier: Topic :: Scientific/Engineering :: Information Analysis
Requires-Dist: python-dateutil
Requires-Dist: future
